appdjango/__init__.py
appdjango/admin.py
appdjango/apps.py
appdjango/models.py
appdjango/tests.py
appdjango/urls.py
appdjango/views.py
appdjango/migrations/0001_initial.py
appdjango/migrations/0002_auto_20190313_1541.py
appdjango/migrations/0003_auto_20190313_1723.py
appdjango/migrations/0004_auto_20190313_1815.py
appdjango/migrations/0005_auto_20190313_2038.py
appdjango/migrations/__init__.py
djangoyz/__init__.py
djangoyz/settings.py
djangoyz/urls.py
djangoyz/wsgi.py
yapayzekadj-0.0.1.dist-info/LICENSE.txt
yapayzekadj-0.0.1.dist-info/METADATA
yapayzekadj-0.0.1.dist-info/WHEEL
yapayzekadj-0.0.1.dist-info/top_level.txt
yapayzekadj-0.0.1.dist-info/RECORD
