Metadata-Version: 2.1
Name: yapayzekadj
Version: 0.0.1
Summary: makine öğrenimi django entegrasyonu
Home-page: https://github.com/oguz687/djangoyz
Author: oguzhan
Author-email: oguzhan_687@hotmail.com
License: MIT
Platform: UNKNOWN
